tongcheng_langfuse/__init__.py
tongcheng_langfuse/_task_manager/ingestion_consumer.py
tongcheng_langfuse/_task_manager/media_manager.py
tongcheng_langfuse/_task_manager/media_upload_consumer.py
tongcheng_langfuse/_task_manager/media_upload_queue.py
tongcheng_langfuse/_task_manager/task_manager.py
tongcheng_langfuse/api/__init__.py
tongcheng_langfuse/api/client.py
tongcheng_langfuse/api/core/__init__.py
tongcheng_langfuse/api/core/api_error.py
tongcheng_langfuse/api/core/client_wrapper.py
tongcheng_langfuse/api/core/datetime_utils.py
tongcheng_langfuse/api/core/file.py
tongcheng_langfuse/api/core/http_client.py
tongcheng_langfuse/api/core/jsonable_encoder.py
tongcheng_langfuse/api/core/pydantic_utilities.py
tongcheng_langfuse/api/core/query_encoder.py
tongcheng_langfuse/api/core/remove_none_from_dict.py
tongcheng_langfuse/api/core/request_options.py
tongcheng_langfuse/api/README.md
tongcheng_langfuse/api/reference.md
tongcheng_langfuse/api/resources/__init__.py
tongcheng_langfuse/api/resources/annotation_queues/__init__.py
tongcheng_langfuse/api/resources/annotation_queues/client.py
tongcheng_langfuse/api/resources/annotation_queues/types/__init__.py
tongcheng_langfuse/api/resources/annotation_queues/types/annotation_queue.py
tongcheng_langfuse/api/resources/annotation_queues/types/annotation_queue_item.py
tongcheng_langfuse/api/resources/annotation_queues/types/annotation_queue_object_type.py
tongcheng_langfuse/api/resources/annotation_queues/types/annotation_queue_status.py
tongcheng_langfuse/api/resources/annotation_queues/types/create_annotation_queue_item_request.py
tongcheng_langfuse/api/resources/annotation_queues/types/delete_annotation_queue_item_response.py
tongcheng_langfuse/api/resources/annotation_queues/types/paginated_annotation_queue_items.py
tongcheng_langfuse/api/resources/annotation_queues/types/paginated_annotation_queues.py
tongcheng_langfuse/api/resources/annotation_queues/types/update_annotation_queue_item_request.py
tongcheng_langfuse-1.0.0.dist-info/entry_points.txt
tongcheng_langfuse-1.0.0.dist-info/LICENSE
tongcheng_langfuse-1.0.0.dist-info/METADATA
tongcheng_langfuse-1.0.0.dist-info/WHEEL
tongcheng_langfuse-1.0.0.dist-info/RECORD
